Newkiton/Newkiton.py
Newkiton/__init__.py
ThermoBeacon/ThermoBeacon.py
ThermoBeacon/__init__.py
tests/__init__.py
tests/discover.py
tests/test_newkiton.py
tests/test_thermobeacon.py
Newkiton-0.1.0.dist-info/LICENSE
Newkiton-0.1.0.dist-info/METADATA
Newkiton-0.1.0.dist-info/WHEEL
Newkiton-0.1.0.dist-info/top_level.txt
Newkiton-0.1.0.dist-info/RECORD
