Metadata-Version: 2.1
Name: Newkiton
Version: 0.1.0
Summary: Newkiton temperature sensor
Home-page: https://github.com/diarmuid/Newkiton
Author: Diarmuid Collins
Author-email: diarmuid.m.collins+github@gmail.com
License: UNKNOWN
Platform: UNKNOWN
Classifier: Programming Language :: Python :: 3
Classifier: License :: OSI Approved :: MIT License
Classifier: Operating System :: OS Independent
Requires-Dist: bluepy
